README.md
setup.py
nem_ed25519/__init__.py
nem_ed25519/base.py
nem_ed25519/encrypt.py
nem_ed25519/key.py
nem_ed25519/signature.py
nem_ed25519/utils.py
nem_ed25519.egg-info/PKG-INFO
nem_ed25519.egg-info/SOURCES.txt
nem_ed25519.egg-info/dependency_links.txt
nem_ed25519.egg-info/requires.txt
nem_ed25519.egg-info/top_level.txt