Metadata-Version: 1.1
Name: nem-ed25519
Version: 0.0.5
Summary: Encryption modules applied to NEM.
Home-page: https://github.com/namuyan/nem-ed25519
Author: namuyan
Author-email: UNKNOWN
License: MIT Licence
Platform: UNKNOWN
Classifier: Programming Language :: Python :: 3
Classifier: Programming Language :: Python :: 3.5
Classifier: Programming Language :: Python :: 3.6
Classifier: License :: OSI Approved :: MIT License
